pyabs.py
setup.py
pyabs.egg-info/PKG-INFO
pyabs.egg-info/SOURCES.txt
pyabs.egg-info/dependency_links.txt
pyabs.egg-info/requires.txt
pyabs.egg-info/top_level.txt
test/__init__.py
test/test.py
test/test_with_celery.py
test/test_with_gevent.py