Metadata-Version: 1.0
Name: pyabs
Version: 1.0.3
Summary: ssh over proxy using paramiko
Home-page: UNKNOWN
Author: gmaclinuxer
Author-email: gmaclinuxer@gmail.com
License: BSD
Platform: UNKNOWN
